{
  "Timestamp": 1778220484258,
  "GameType": 0,
  "GridOrientation": 0,
  "XCells": 3,
  "YCells": 3,
  "Tiles": [
    [
      {
        "TileType": 1
      },
      {
        "TileType": 6,
        "UnlockLevel": 51,
        "Stacks": [
          3,
          0,
          1,
          0,
          1,
          6
        ]
      },
      {
        "TileType": 6,
        "UnlockLevel": 51,
        "Stacks": [
          1,
          5,
          2,
          4,
          2,
          1
        ]
      }
    ],
    [
      {
        "TileType": 6,
        "UnlockLevel": 118,
        "Stacks": [
          0,
          6,
          0,
          3
        ]
      },
      {
        "TileType": 6,
        "UnlockLevel": 51,
        "Stacks": [
          4,
          4,
          5,
          4,
          1
        ]
      },
      {
        "TileType": 0
      }
    ],
    [
      {
        "TileType": 1
      },
      {
        "TileType": 4,
        "Level": 4
      },
      {
        "TileType": 6,
        "UnlockLevel": 51,
        "Stacks": [
          0,
          3,
          1,
          6,
          1
        ]
      }
    ]
  ]
}